megara_visual_glue/__init__.py
megara_visual_glue/data_viewer.py
megara_visual_glue-0.1.1.dist-info/LICENSE
megara_visual_glue-0.1.1.dist-info/METADATA
megara_visual_glue-0.1.1.dist-info/WHEEL
megara_visual_glue-0.1.1.dist-info/entry_points.txt
megara_visual_glue-0.1.1.dist-info/top_level.txt
megara_visual_glue-0.1.1.dist-info/RECORD
