Metadata-Version: 2.1
Name: megara-visual-glue
Version: 0.1.1
Summary: MEGARA visualization package
Author-email: Sherezade JM <shjuarez@ucm.es>
License: MIT
Project-URL: Homepage, https://github.com/zadejuarez/GlueMegara
Project-URL: Repository, https://github.com/zadejuarez/GlueMegara.git
Requires-Python: >=3.8
License-File: LICENSE
Requires-Dist: numpy
Requires-Dist: astropy
Requires-Dist: matplotlib
Requires-Dist: megaradrp
Requires-Dist: qtpy
Requires-Dist: glueviz
